QMDown/__init__.py
QMDown/__main__.py
QMDown/api.py
QMDown/cli.py
QMDown/model.py
QMDown/extractor/__init__.py
QMDown/extractor/_abc.py
QMDown/extractor/album.py
QMDown/extractor/singer.py
QMDown/extractor/song.py
QMDown/extractor/songlist.py
QMDown/extractor/top.py
QMDown/processor/downloader.py
QMDown/processor/handler.py
QMDown/utils/async_typer.py
QMDown/utils/cache.py
QMDown/utils/lrcparser.py
QMDown/utils/priority.py
QMDown/utils/progress.py
QMDown/utils/tag.py
QMDown/utils/utils.py
qmdown-0.2.3.dist-info/METADATA
qmdown-0.2.3.dist-info/WHEEL
qmdown-0.2.3.dist-info/entry_points.txt
qmdown-0.2.3.dist-info/licenses/LICENSE
qmdown-0.2.3.dist-info/RECORD
