Metadata-Version: 2.4
Name: QMDown
Version: 0.2.3
Summary: QQ音乐解析/下载工具
Author-email: Luren <68656403+luren-dc@users.noreply.github.com>
License: MIT
License-File: LICENSE
Requires-Python: <3.13,>=3.10
Requires-Dist: httpx>=0.27.2
Requires-Dist: mutagen>=1.47.0
Requires-Dist: pillow>=11.0.0
Requires-Dist: pydantic>=2.10.4
Requires-Dist: pyzbar>=0.1.9
Requires-Dist: qqmusic-api-python>=0.1.10
Requires-Dist: qrcode>=8.0
Requires-Dist: tenacity>=9.0.0
Requires-Dist: typer>=0.13.0
